consolio/__init__.py
consolio-0.1.15.dist-info/licenses/LICENSE
consolio-0.1.15.dist-info/METADATA
consolio-0.1.15.dist-info/WHEEL
consolio-0.1.15.dist-info/top_level.txt
consolio-0.1.15.dist-info/RECORD
