Metadata-Version: 2.4
Name: consolio
Version: 0.1.15
Summary: A simple terminal I/O utility with spinner animation
Author-email: "Ioannis D (devcoons)" <support@devcoons.com>
License: MIT License
Project-URL: Homepage, https://github.com/devcoons/consolio
Project-URL: Issues, https://github.com/devcoons/consolio/issues
Keywords: consolio,terminal,color
Classifier: Development Status :: 5 - Production/Stable
Classifier: Intended Audience :: Developers
Classifier: Natural Language :: English
Classifier: License :: OSI Approved :: MIT License
Classifier: Operating System :: OS Independent
Classifier: Programming Language :: Python :: 3.8
Classifier: Programming Language :: Python :: 3.9
Classifier: Programming Language :: Python :: 3.10
Classifier: Programming Language :: Python :: 3.11
Classifier: Programming Language :: Python :: 3.12
Classifier: Programming Language :: Python :: Implementation :: PyPy
Requires-Python: >=3.9
License-File: LICENSE
Provides-Extra: dev
Requires-Dist: pip-tools; extra == "dev"
Dynamic: license-file
